oci_documentation_mcp_server/__init__.py
oci_documentation_mcp_server/models.py
oci_documentation_mcp_server/server.py
oci_documentation_mcp_server/util.py
oci_documentation_mcp_server-0.0.1.dist-info/METADATA
oci_documentation_mcp_server-0.0.1.dist-info/WHEEL
oci_documentation_mcp_server-0.0.1.dist-info/entry_points.txt
oci_documentation_mcp_server-0.0.1.dist-info/licenses/LICENSE
oci_documentation_mcp_server-0.0.1.dist-info/RECORD
