Metadata-Version: 2.4
Name: oci-documentation-mcp-server
Version: 0.0.1
Summary: An  Model Context Protocol (MCP) server for OCI Documentation
License-File: LICENSE
Requires-Python: >=3.10
Requires-Dist: beautifulsoup4>=4.12.0
Requires-Dist: googlesearch-python>=1.3.0
Requires-Dist: httpx>=0.27.0
Requires-Dist: loguru>=0.7.0
Requires-Dist: markdownify>=1.1.0
Requires-Dist: mcp[cli]>=1.6.0
Requires-Dist: pydantic>=2.10.6
